LICENSE
MANIFEST.in
README.rst
setup.cfg
setup.py
pmacparser/__init__.py
pmacparser/pmac_lexer.py
pmacparser/pmac_parser.py
pmacparser/version.py
pmacparser.egg-info/PKG-INFO
pmacparser.egg-info/SOURCES.txt
pmacparser.egg-info/dependency_links.txt
pmacparser.egg-info/not-zip-safe
pmacparser.egg-info/requires.txt
pmacparser.egg-info/top_level.txt