Metadata-Version: 1.1
Name: pmacparser
Version: 0.2
Summary: PMAC parser and kinematics emulator
Home-page: https://github.com/dls-controls/pmacparser
Author: Matt Taylor
Author-email: matthew.taylor@diamond.ac.uk
License: APACHE
Platform: UNKNOWN
Classifier: Development Status :: 3 - Alpha
Classifier: Intended Audience :: Developers
Classifier: Natural Language :: English
Classifier: Operating System :: POSIX :: Linux
Classifier: Programming Language :: Python :: 2.7
